lupislabs/__init__.py
lupislabs/cost_utils.py
lupislabs/endpoints.py
lupislabs/http_interceptor.py
lupislabs/sdk.py
lupislabs/sensitive_data_filter.py
lupislabs/trace_collector.py
lupislabs/tracer.py
lupislabs/types.py
lupislabs/providers/__init__.py
lupislabs/providers/anthropic_handler.py
lupislabs/providers/gemini_handler.py
lupislabs/providers/openai_handler.py
lupislabs/providers/provider_detector.py
lupislabs-1.0.4.dist-info/licenses/LICENSE
lupislabs-1.0.4.dist-info/METADATA
lupislabs-1.0.4.dist-info/WHEEL
lupislabs-1.0.4.dist-info/top_level.txt
lupislabs-1.0.4.dist-info/RECORD
