Metadata-Version: 2.4
Name: lupislabs
Version: 1.0.4
Summary: LupisLabs Python SDK for AI application tracing and monitoring
Author-email: LupisLabs <team@lupislabs.com>
Maintainer-email: LupisLabs <team@lupislabs.com>
License: MIT
Project-URL: Homepage, https://github.com/lupislabs/lupis-python-sdk
Project-URL: Documentation, https://github.com/lupislabs/lupis-python-sdk#readme
Project-URL: Repository, https://github.com/lupislabs/lupis-python-sdk
Project-URL: Issues, https://github.com/lupislabs/lupis-python-sdk/issues
Keywords: ai,tracing,lupislabs,sdk
Classifier: Development Status :: 4 - Beta
Classifier: Intended Audience :: Developers
Classifier: License :: OSI Approved :: MIT License
Classifier: Operating System :: OS Independent
Classifier: Programming Language :: Python :: 3
Classifier: Programming Language :: Python :: 3.8
Classifier: Programming Language :: Python :: 3.9
Classifier: Programming Language :: Python :: 3.10
Classifier: Programming Language :: Python :: 3.11
Classifier: Programming Language :: Python :: 3.12
Classifier: Topic :: Software Development :: Libraries :: Python Modules
Classifier: Topic :: System :: Monitoring
Requires-Python: >=3.8
License-File: LICENSE
Requires-Dist: requests>=2.25.0
Provides-Extra: dev
Requires-Dist: pytest>=7.0.0; extra == "dev"
Requires-Dist: pytest-asyncio>=0.21.0; extra == "dev"
Requires-Dist: black>=22.0.0; extra == "dev"
Requires-Dist: isort>=5.10.0; extra == "dev"
Requires-Dist: mypy>=1.0.0; extra == "dev"
Requires-Dist: flake8>=5.0.0; extra == "dev"
Dynamic: license-file
